[
  {
    "id": "01",
    "file": "C:/Users/Admin/Downloads/FSave_Reels_Double-sided-LED-faux-gypsum-linear-ligh_Media_1529320085577240_002_720p.mp4",
    "sheetPath": "C:\\fastcome\\.video-summary-frames\\01-sheet.png",
    "framePaths": [
      "C:\\fastcome\\.video-summary-frames\\01-01.png",
      "C:\\fastcome\\.video-summary-frames\\01-02.png",
      "C:\\fastcome\\.video-summary-frames\\01-03.png",
      "C:\\fastcome\\.video-summary-frames\\01-04.png",
      "C:\\fastcome\\.video-summary-frames\\01-05.png",
      "C:\\fastcome\\.video-summary-frames\\01-06.png",
      "C:\\fastcome\\.video-summary-frames\\01-07.png",
      "C:\\fastcome\\.video-summary-frames\\01-08.png",
      "C:\\fastcome\\.video-summary-frames\\01-09.png",
      "C:\\fastcome\\.video-summary-frames\\01-10.png",
      "C:\\fastcome\\.video-summary-frames\\01-11.png",
      "C:\\fastcome\\.video-summary-frames\\01-12.png"
    ],
    "duration": 15.166666666666666,
    "width": 720,
    "height": 1280,
    "fps": 30.0
  },
  {
    "id": "02",
    "file": "C:/Users/Admin/Downloads/FSave_Reels_Sau-hon-7000-du-an-thi-day-chinh-la-em-t_Media_2019669468959495_002_720p.mp4",
    "sheetPath": "C:\\fastcome\\.video-summary-frames\\02-sheet.png",
    "framePaths": [
      "C:\\fastcome\\.video-summary-frames\\02-01.png",
      "C:\\fastcome\\.video-summary-frames\\02-02.png",
      "C:\\fastcome\\.video-summary-frames\\02-03.png",
      "C:\\fastcome\\.video-summary-frames\\02-04.png",
      "C:\\fastcome\\.video-summary-frames\\02-05.png",
      "C:\\fastcome\\.video-summary-frames\\02-06.png",
      "C:\\fastcome\\.video-summary-frames\\02-07.png",
      "C:\\fastcome\\.video-summary-frames\\02-08.png",
      "C:\\fastcome\\.video-summary-frames\\02-09.png",
      "C:\\fastcome\\.video-summary-frames\\02-10.png",
      "C:\\fastcome\\.video-summary-frames\\02-11.png",
      "C:\\fastcome\\.video-summary-frames\\02-12.png",
      "C:\\fastcome\\.video-summary-frames\\02-13.png",
      "C:\\fastcome\\.video-summary-frames\\02-14.png",
      "C:\\fastcome\\.video-summary-frames\\02-15.png",
      "C:\\fastcome\\.video-summary-frames\\02-16.png"
    ],
    "duration": 57.46666666666667,
    "width": 720,
    "height": 1280,
    "fps": 30.0
  },
  {
    "id": "03",
    "file": "C:/Users/Admin/Downloads/FSave_Reels_Bi-quyet-chon-chau-rua-bat-99-cac-bac-kh_Media_1108324518086454_002_720p.mp4",
    "sheetPath": "C:\\fastcome\\.video-summary-frames\\03-sheet.png",
    "framePaths": [
      "C:\\fastcome\\.video-summary-frames\\03-01.png",
      "C:\\fastcome\\.video-summary-frames\\03-02.png",
      "C:\\fastcome\\.video-summary-frames\\03-03.png",
      "C:\\fastcome\\.video-summary-frames\\03-04.png",
      "C:\\fastcome\\.video-summary-frames\\03-05.png",
      "C:\\fastcome\\.video-summary-frames\\03-06.png",
      "C:\\fastcome\\.video-summary-frames\\03-07.png",
      "C:\\fastcome\\.video-summary-frames\\03-08.png",
      "C:\\fastcome\\.video-summary-frames\\03-09.png",
      "C:\\fastcome\\.video-summary-frames\\03-10.png",
      "C:\\fastcome\\.video-summary-frames\\03-11.png",
      "C:\\fastcome\\.video-summary-frames\\03-12.png",
      "C:\\fastcome\\.video-summary-frames\\03-13.png",
      "C:\\fastcome\\.video-summary-frames\\03-14.png",
      "C:\\fastcome\\.video-summary-frames\\03-15.png",
      "C:\\fastcome\\.video-summary-frames\\03-16.png"
    ],
    "duration": 135.83333333333334,
    "width": 720,
    "height": 1280,
    "fps": 30.0
  },
  {
    "id": "04",
    "file": "C:/Users/Admin/Downloads/FSave_Reels_Muon-nha-dep-ma-khong-ton-kem-hay-nho-ng_Media_728703696851897_002_720p.mp4",
    "sheetPath": "C:\\fastcome\\.video-summary-frames\\04-sheet.png",
    "framePaths": [
      "C:\\fastcome\\.video-summary-frames\\04-01.png",
      "C:\\fastcome\\.video-summary-frames\\04-02.png",
      "C:\\fastcome\\.video-summary-frames\\04-03.png",
      "C:\\fastcome\\.video-summary-frames\\04-04.png",
      "C:\\fastcome\\.video-summary-frames\\04-05.png",
      "C:\\fastcome\\.video-summary-frames\\04-06.png",
      "C:\\fastcome\\.video-summary-frames\\04-07.png",
      "C:\\fastcome\\.video-summary-frames\\04-08.png",
      "C:\\fastcome\\.video-summary-frames\\04-09.png",
      "C:\\fastcome\\.video-summary-frames\\04-10.png",
      "C:\\fastcome\\.video-summary-frames\\04-11.png",
      "C:\\fastcome\\.video-summary-frames\\04-12.png",
      "C:\\fastcome\\.video-summary-frames\\04-13.png",
      "C:\\fastcome\\.video-summary-frames\\04-14.png",
      "C:\\fastcome\\.video-summary-frames\\04-15.png",
      "C:\\fastcome\\.video-summary-frames\\04-16.png"
    ],
    "duration": 110.4,
    "width": 720,
    "height": 1280,
    "fps": 30.0
  },
  {
    "id": "05",
    "file": "C:/Users/Admin/Downloads/FSave_Reels_Tai-sao-nha-nguoi-ta-luon-moi-con-nha-ba_Media_757338463838808_002_720p.mp4",
    "sheetPath": "C:\\fastcome\\.video-summary-frames\\05-sheet.png",
    "framePaths": [
      "C:\\fastcome\\.video-summary-frames\\05-01.png",
      "C:\\fastcome\\.video-summary-frames\\05-02.png",
      "C:\\fastcome\\.video-summary-frames\\05-03.png",
      "C:\\fastcome\\.video-summary-frames\\05-04.png",
      "C:\\fastcome\\.video-summary-frames\\05-05.png",
      "C:\\fastcome\\.video-summary-frames\\05-06.png",
      "C:\\fastcome\\.video-summary-frames\\05-07.png",
      "C:\\fastcome\\.video-summary-frames\\05-08.png",
      "C:\\fastcome\\.video-summary-frames\\05-09.png",
      "C:\\fastcome\\.video-summary-frames\\05-10.png",
      "C:\\fastcome\\.video-summary-frames\\05-11.png",
      "C:\\fastcome\\.video-summary-frames\\05-12.png",
      "C:\\fastcome\\.video-summary-frames\\05-13.png",
      "C:\\fastcome\\.video-summary-frames\\05-14.png",
      "C:\\fastcome\\.video-summary-frames\\05-15.png",
      "C:\\fastcome\\.video-summary-frames\\05-16.png"
    ],
    "duration": 129.66666666666666,
    "width": 720,
    "height": 1280,
    "fps": 30.0
  },
  {
    "id": "06",
    "file": "C:/Users/Admin/Downloads/FSave_Reels_7-chi-tiet-nho-co-the-pha-nat-ca-can-bep_Media_1261219775333907_002_720p.mp4",
    "sheetPath": "C:\\fastcome\\.video-summary-frames\\06-sheet.png",
    "framePaths": [
      "C:\\fastcome\\.video-summary-frames\\06-01.png",
      "C:\\fastcome\\.video-summary-frames\\06-02.png",
      "C:\\fastcome\\.video-summary-frames\\06-03.png",
      "C:\\fastcome\\.video-summary-frames\\06-04.png",
      "C:\\fastcome\\.video-summary-frames\\06-05.png",
      "C:\\fastcome\\.video-summary-frames\\06-06.png",
      "C:\\fastcome\\.video-summary-frames\\06-07.png",
      "C:\\fastcome\\.video-summary-frames\\06-08.png",
      "C:\\fastcome\\.video-summary-frames\\06-09.png",
      "C:\\fastcome\\.video-summary-frames\\06-10.png",
      "C:\\fastcome\\.video-summary-frames\\06-11.png",
      "C:\\fastcome\\.video-summary-frames\\06-12.png",
      "C:\\fastcome\\.video-summary-frames\\06-13.png",
      "C:\\fastcome\\.video-summary-frames\\06-14.png",
      "C:\\fastcome\\.video-summary-frames\\06-15.png",
      "C:\\fastcome\\.video-summary-frames\\06-16.png"
    ],
    "duration": 167.13333333333333,
    "width": 720,
    "height": 1280,
    "fps": 30.0
  },
  {
    "id": "07",
    "file": "C:/Users/Admin/Downloads/FSave_Reels_Dung-mu-quang-lap-8-mon-nay-trong-phong-_Media_2055547868625084_003_720p.mp4",
    "sheetPath": "C:\\fastcome\\.video-summary-frames\\07-sheet.png",
    "framePaths": [
      "C:\\fastcome\\.video-summary-frames\\07-01.png",
      "C:\\fastcome\\.video-summary-frames\\07-02.png",
      "C:\\fastcome\\.video-summary-frames\\07-03.png",
      "C:\\fastcome\\.video-summary-frames\\07-04.png",
      "C:\\fastcome\\.video-summary-frames\\07-05.png",
      "C:\\fastcome\\.video-summary-frames\\07-06.png",
      "C:\\fastcome\\.video-summary-frames\\07-07.png",
      "C:\\fastcome\\.video-summary-frames\\07-08.png",
      "C:\\fastcome\\.video-summary-frames\\07-09.png",
      "C:\\fastcome\\.video-summary-frames\\07-10.png",
      "C:\\fastcome\\.video-summary-frames\\07-11.png",
      "C:\\fastcome\\.video-summary-frames\\07-12.png",
      "C:\\fastcome\\.video-summary-frames\\07-13.png",
      "C:\\fastcome\\.video-summary-frames\\07-14.png",
      "C:\\fastcome\\.video-summary-frames\\07-15.png",
      "C:\\fastcome\\.video-summary-frames\\07-16.png"
    ],
    "duration": 152.6,
    "width": 720,
    "height": 1280,
    "fps": 30.0
  },
  {
    "id": "08",
    "file": "C:/Users/Admin/Downloads/FSave_Reels_7-diem-song-con-phai-kiem-tra-ngay-khi-d_Media_1714986366131263_002_720p.mp4",
    "sheetPath": "C:\\fastcome\\.video-summary-frames\\08-sheet.png",
    "framePaths": [
      "C:\\fastcome\\.video-summary-frames\\08-01.png",
      "C:\\fastcome\\.video-summary-frames\\08-02.png",
      "C:\\fastcome\\.video-summary-frames\\08-03.png",
      "C:\\fastcome\\.video-summary-frames\\08-04.png",
      "C:\\fastcome\\.video-summary-frames\\08-05.png",
      "C:\\fastcome\\.video-summary-frames\\08-06.png",
      "C:\\fastcome\\.video-summary-frames\\08-07.png",
      "C:\\fastcome\\.video-summary-frames\\08-08.png",
      "C:\\fastcome\\.video-summary-frames\\08-09.png",
      "C:\\fastcome\\.video-summary-frames\\08-10.png",
      "C:\\fastcome\\.video-summary-frames\\08-11.png",
      "C:\\fastcome\\.video-summary-frames\\08-12.png",
      "C:\\fastcome\\.video-summary-frames\\08-13.png",
      "C:\\fastcome\\.video-summary-frames\\08-14.png",
      "C:\\fastcome\\.video-summary-frames\\08-15.png",
      "C:\\fastcome\\.video-summary-frames\\08-16.png"
    ],
    "duration": 196.16666666666666,
    "width": 720,
    "height": 1280,
    "fps": 30.0
  },
  {
    "id": "09",
    "file": "C:/Users/Admin/Downloads/FSave_Reels_Muon-nha-o-ben-dep-lau-dung-bo-qua-5-kie_Media_1508948423744455_002_720p.mp4",
    "sheetPath": "C:\\fastcome\\.video-summary-frames\\09-sheet.png",
    "framePaths": [
      "C:\\fastcome\\.video-summary-frames\\09-01.png",
      "C:\\fastcome\\.video-summary-frames\\09-02.png",
      "C:\\fastcome\\.video-summary-frames\\09-03.png",
      "C:\\fastcome\\.video-summary-frames\\09-04.png",
      "C:\\fastcome\\.video-summary-frames\\09-05.png",
      "C:\\fastcome\\.video-summary-frames\\09-06.png",
      "C:\\fastcome\\.video-summary-frames\\09-07.png",
      "C:\\fastcome\\.video-summary-frames\\09-08.png",
      "C:\\fastcome\\.video-summary-frames\\09-09.png",
      "C:\\fastcome\\.video-summary-frames\\09-10.png",
      "C:\\fastcome\\.video-summary-frames\\09-11.png",
      "C:\\fastcome\\.video-summary-frames\\09-12.png",
      "C:\\fastcome\\.video-summary-frames\\09-13.png",
      "C:\\fastcome\\.video-summary-frames\\09-14.png",
      "C:\\fastcome\\.video-summary-frames\\09-15.png",
      "C:\\fastcome\\.video-summary-frames\\09-16.png"
    ],
    "duration": 162.46666666666667,
    "width": 720,
    "height": 1280,
    "fps": 30.0
  },
  {
    "id": "10",
    "file": "C:/Users/Admin/Downloads/FSave_Reels_Lam-phong-tam-ma-bo-qua-7-dieu-nay-thi-s_Media_1172729604572669_002_720p.mp4",
    "sheetPath": "C:\\fastcome\\.video-summary-frames\\10-sheet.png",
    "framePaths": [
      "C:\\fastcome\\.video-summary-frames\\10-01.png",
      "C:\\fastcome\\.video-summary-frames\\10-02.png",
      "C:\\fastcome\\.video-summary-frames\\10-03.png",
      "C:\\fastcome\\.video-summary-frames\\10-04.png",
      "C:\\fastcome\\.video-summary-frames\\10-05.png",
      "C:\\fastcome\\.video-summary-frames\\10-06.png",
      "C:\\fastcome\\.video-summary-frames\\10-07.png",
      "C:\\fastcome\\.video-summary-frames\\10-08.png",
      "C:\\fastcome\\.video-summary-frames\\10-09.png",
      "C:\\fastcome\\.video-summary-frames\\10-10.png",
      "C:\\fastcome\\.video-summary-frames\\10-11.png",
      "C:\\fastcome\\.video-summary-frames\\10-12.png",
      "C:\\fastcome\\.video-summary-frames\\10-13.png",
      "C:\\fastcome\\.video-summary-frames\\10-14.png",
      "C:\\fastcome\\.video-summary-frames\\10-15.png",
      "C:\\fastcome\\.video-summary-frames\\10-16.png"
    ],
    "duration": 251.7,
    "width": 720,
    "height": 1280,
    "fps": 30.0
  },
  {
    "id": "11",
    "file": "C:/Users/Admin/Downloads/FSave_Reels_Bi-quyet-lat-gach-de-khong-hoi-han-yenth_Media_1318416846703861_002_720p.mp4",
    "sheetPath": "C:\\fastcome\\.video-summary-frames\\11-sheet.png",
    "framePaths": [
      "C:\\fastcome\\.video-summary-frames\\11-01.png",
      "C:\\fastcome\\.video-summary-frames\\11-02.png",
      "C:\\fastcome\\.video-summary-frames\\11-03.png",
      "C:\\fastcome\\.video-summary-frames\\11-04.png",
      "C:\\fastcome\\.video-summary-frames\\11-05.png",
      "C:\\fastcome\\.video-summary-frames\\11-06.png",
      "C:\\fastcome\\.video-summary-frames\\11-07.png",
      "C:\\fastcome\\.video-summary-frames\\11-08.png",
      "C:\\fastcome\\.video-summary-frames\\11-09.png",
      "C:\\fastcome\\.video-summary-frames\\11-10.png",
      "C:\\fastcome\\.video-summary-frames\\11-11.png",
      "C:\\fastcome\\.video-summary-frames\\11-12.png",
      "C:\\fastcome\\.video-summary-frames\\11-13.png",
      "C:\\fastcome\\.video-summary-frames\\11-14.png",
      "C:\\fastcome\\.video-summary-frames\\11-15.png",
      "C:\\fastcome\\.video-summary-frames\\11-16.png"
    ],
    "duration": 168.76666666666668,
    "width": 720,
    "height": 1280,
    "fps": 30.0
  }
]